fast_down_upload/DownLoad.py
fast_down_upload/StartDownUpload.py
fast_down_upload/UploadFile.py
fast_down_upload/__init__.py
fast_down_upload/configs.py
fast_down_upload-1.7.dist-info/LICENSE.rst
fast_down_upload-1.7.dist-info/METADATA
fast_down_upload-1.7.dist-info/WHEEL
fast_down_upload-1.7.dist-info/top_level.txt
fast_down_upload-1.7.dist-info/RECORD
