Metadata-Version: 2.1
Name: fast-down-upload
Version: 1.7
Summary: 分布式文件下载上传
Home-page: https://github.com/abo123456789/FileDownUpload.git
Author: cc
Author-email: abcdef123456chen@sohu.com
Maintainer: cc
Maintainer-email: abcdef123456chen@sohu.com
License: MIT License
Platform: all
Classifier: Development Status :: 4 - Beta
Classifier: Operating System :: OS Independent
Classifier: Intended Audience :: Developers
Classifier: License :: OSI Approved :: MIT License
Classifier: Programming Language :: Python
Classifier: Programming Language :: Python :: Implementation
Classifier: Programming Language :: Python :: 3.6
Classifier: Topic :: Software Development :: Libraries
Requires-Dist: requests (>=2.22.0)
Requires-Dist: tomorrow3 (>=1.1.0)
Requires-Dist: retrying (>=1.3.3)
Requires-Dist: py-log (>=1.9)
Requires-Dist: redis-queue-tool (>=4.3.8)
